README.md
setup.cfg
setup.py
pdistributionpackage/Binomialdistribution.py
pdistributionpackage/Gaussiandistribution.py
pdistributionpackage/Generaldistribution.py
pdistributionpackage/__init__.py
pdistributionpackage.egg-info/PKG-INFO
pdistributionpackage.egg-info/SOURCES.txt
pdistributionpackage.egg-info/dependency_links.txt
pdistributionpackage.egg-info/not-zip-safe
pdistributionpackage.egg-info/top_level.txt