Metadata-Version: 1.0
Name: pdistributionpackage
Version: 0.1
Summary: Gaussian and Binomial distributions
Home-page: UNKNOWN
Author: Pushkar Mahajan
Author-email: pushkarmahajan123@gmail.com
License: UNKNOWN
Platform: UNKNOWN
